Design/netlist_after_synthesis/usr_nbit.v

module usr_nbit(select, parallelin, left, right, parallelout, clk, rst);
  wire _00_;
  wire _01_;
  wire _02_;
  wire _03_;
  wire _04_;
  wire _05_;
  wire _06_;
  wire _07_;
  wire _08_;
  wire _09_;
  wire _10_;
  wire _11_;
  wire _12_;
  wire _13_;
  wire _14_;
  wire _15_;
  wire _16_;
  wire _17_;
  wire _18_;
  input clk;
  input left;
  input [3:0] parallelin;
  output [3:0] parallelout;
  input right;
  input rst;
  input [1:0] select;
  sky130_fd_sc_hd__or2_2 _19_ (
    .A(select[0]),
    .B(select[1]),
    .X(_09_)
  );
  sky130_fd_sc_hd__inv_2 _20_ (
    .A(_09_),
    .Y(_10_)
  );
  sky130_fd_sc_hd__inv_2 _21_ (
    .A(rst),
    .Y(_11_)
  );
  sky130_fd_sc_hd__o221a_2 _22_ (
    .A1(_15_),
    .A2(_10_),
    .B1(parallelout[1]),
    .B2(_09_),
    .C1(_11_),
    .X(_07_)
  );
  sky130_fd_sc_hd__o221a_2 _23_ (
    .A1(_17_),
    .A2(_10_),
    .B1(parallelout[0]),
    .B2(_09_),
    .C1(_11_),
    .X(_06_)
  );
  sky130_fd_sc_hd__o221a_2 _24_ (
    .A1(_16_),
    .A2(_10_),
    .B1(parallelout[2]),
    .B2(_09_),
    .C1(_11_),
    .X(_05_)
  );
  sky130_fd_sc_hd__buf_1 _25_ (
    .A(select[0]),
    .X(_12_)
  );
  sky130_fd_sc_hd__inv_2 _26_ (
    .A(_12_),
    .Y(_00_)
  );
  sky130_fd_sc_hd__buf_1 _27_ (
    .A(select[1]),
    .X(_13_)
  );
  sky130_fd_sc_hd__nor2_2 _28_ (
    .A(_00_),
    .B(_13_),
    .Y(_14_)
  );
  sky130_fd_sc_hd__a32o_2 _29_ (
    .A1(_12_),
    .A2(_13_),
    .A3(parallelin[0]),
    .B1(parallelout[1]),
    .B2(_14_),
    .X(_01_)
  );
  sky130_fd_sc_hd__a32o_2 _30_ (
    .A1(_12_),
    .A2(_13_),
    .A3(parallelin[3]),
    .B1(right),
    .B2(_14_),
    .X(_02_)
  );
  sky130_fd_sc_hd__a32o_2 _31_ (
    .A1(_12_),
    .A2(_13_),
    .A3(parallelin[1]),
    .B1(parallelout[2]),
    .B2(_14_),
    .X(_03_)
  );
  sky130_fd_sc_hd__a32o_2 _32_ (
    .A1(_12_),
    .A2(_13_),
    .A3(parallelin[2]),
    .B1(parallelout[3]),
    .B2(_14_),
    .X(_04_)
  );
  sky130_fd_sc_hd__o221a_2 _33_ (
    .A1(_18_),
    .A2(_10_),
    .B1(parallelout[3]),
    .B2(_09_),
    .C1(_11_),
    .X(_08_)
  );
  sky130_fd_sc_hd__mux2_1 _34_ (
    .A0(_01_),
    .A1(left),
    .S(_00_),
    .X(_17_)
  );
  sky130_fd_sc_hd__mux2_1 _35_ (
    .A0(_02_),
    .A1(parallelout[2]),
    .S(_00_),
    .X(_18_)
  );
  sky130_fd_sc_hd__mux2_1 _36_ (
    .A0(_03_),
    .A1(parallelout[0]),
    .S(_00_),
    .X(_15_)
  );
  sky130_fd_sc_hd__mux2_1 _37_ (
    .A0(_04_),
    .A1(parallelout[1]),
    .S(_00_),
    .X(_16_)
  );
  sky130_fd_sc_hd__dfxtp_2 _38_ (
    .CLK(clk),
    .D(_05_),
    .Q(parallelout[2])
  );
  sky130_fd_sc_hd__dfxtp_2 _39_ (
    .CLK(clk),
    .D(_06_),
    .Q(parallelout[0])
  );
  sky130_fd_sc_hd__dfxtp_2 _40_ (
    .CLK(clk),
    .D(_07_),
    .Q(parallelout[1])
  );
  sky130_fd_sc_hd__dfxtp_2 _41_ (
    .CLK(clk),
    .D(_08_),
    .Q(parallelout[3])
  );
endmodule





//module a32o_2
module sky130_fd_sc_hd__a32o_2 (X  ,A1  ,A2  ,A3  ,B1  ,B2);
    output X   ;
    input  A1  ;
    input  A2  ;
    input  A3  ;
    input  B1  ;
    input  B2  ;
    wire and0_out;
    wire and1_out;
    and                                and0        (and0_out         , A3, A1, A2           );
    and                                and1        (and1_out         , B1, B2               );
    or                                 or0         (X        , and1_out, and0_out   );

endmodule


//module buf_1
module   sky130_fd_sc_hd__buf_1 (A,X);
input A;
output X;

buf buf1 (X,A);

endmodule



//module dfxtp_2
module  sky130_fd_sc_hd__dfxtp_2 (CLK,D,Q);
input D, CLK;
output Q;
reg Q;

always@(posedge CLK)
begin
	Q<=D;
end
endmodule


//module inv_2
module sky130_fd_sc_hd__inv_2 (A,Y);
input A;
output Y;

not not1 (Y,A);

endmodule


//module mux2_1
module  sky130_fd_sc_hd__mux2_1 (A0,A1,S,X);
input A0,A1,S;
output X;

wire not_out,and_out1,and_out0;

not not0 (not_out,S);
and and0 (and_out0,not_out,A0);
and and1 (and_out1,S,A1);
or or0 (X,and_out0,and_out1);

endmodule


//module nor2_2
module   sky130_fd_sc_hd__nor2_2 (A,B,Y);
input A,B;
output Y;

nor nor1 (Y,A,B);
endmodule


//module o221a_2
module sky130_fd_sc_hd__o221a_2 (X   ,A1  ,A2  ,B1  ,B2  ,C1  ,);
    output X   ;
    input  A1  ;
    input  A2  ;
    input  B1  ;
    input  B2  ;
    input  C1  ;
    wire or0_out          ;
    wire or1_out          ;
    or                                 or0         (or0_out          , B2, B1                );
    or                                 or1         (or1_out          , A2, A1                );
    and                                and0        (X                , or0_out, or1_out, C1  );

endmodule


//module or2_2
module sky130_fd_sc_hd__or2_2(A,B,X);
input A,B;
output X;

or or1 (X,A,B);

endmodule

Design/netlist/usr_nbit_tb.v
`timescale 1ns / 1ps
`include "usr_nbit.v"
module usr_nbit_tb;
  parameter size =4;
  reg [1:0]select;
  reg [size-1:0] parallelin;
  reg left;
  reg right;
  reg clk,rst;
  wire [size-1:0] parallelout;

usr_nbit instantiation(.select(select), .parallelin(parallelin), .left(left), .right(right), .clk(clk), .rst(rst), .parallelout(parallelout));
initial begin

    $dumpfile("usr_n.vcd");
    $dumpvars(0, usr_nbit_tb);
    clk=0;
    #1;
    rst=1;
    select = 2'b00;
    left = 1'b1;
    right = 1'b1;
    parallelin = 4'b0000;
    #1;
    clk=1;
    #2
    clk=0;
    #1;
    rst=0;
    #1;
    clk=1;
    #2;
    clk=0;
    #1;
    select = 2'b11;
    parallelin = 4'b0110;
    #1;
    clk=1;
    #2;
    clk=0;
    #1;
    select = 2'b00;
    parallelin = 4'b1010;
    #1;
    clk=1;
    #2;
    clk=0;
    #1;
    select = 2'b01;
    parallelin = 4'b1010;
    #1;
    clk=1;
    #2;
    clk=0;
    #1;
    select = 2'b10;
    parallelin = 4'b1010;
    #1;
    clk=1;
    #2;
    clk=0;
    #1;
    select = 2'b00;
    parallelin = 4'b0001;
    #1;
    clk=1;
    #2;
    clk=0;
    #1;
    select = 2'b01;
    parallelin = 4'b1010;
    #1;
    clk=1;
    #2;
    clk=0;
    #1;
    select = 2'b10;
    parallelin = 4'b1010;
    #1;
    clk=1;
end

endmodule

Design/netlist_after_synthesis/usr_n.vcd
$date
	Fri Nov 19 17:14:42 2021
$end
$version
	Icarus Verilog
$end
$timescale
	1ps
$end
$scope module usr_nbit_tb $end
$var wire 4 ! parallelout [3:0] $end
$var reg 1 " clk $end
$var reg 1 # left $end
$var reg 4 $ parallelin [3:0] $end
$var reg 1 % right $end
$var reg 1 & rst $end
$var reg 2 ' select [1:0] $end
$scope module instantiation $end
$var wire 1 " clk $end
$var wire 1 # left $end
$var wire 4 ( parallelin [3:0] $end
$var wire 1 % right $end
$var wire 1 & rst $end
$var wire 2 ) select [1:0] $end
$var wire 4 * parallelout [3:0] $end
$var wire 1 + _18_ $end
$var wire 1 , _17_ $end
$var wire 1 - _16_ $end
$var wire 1 . _15_ $end
$var wire 1 / _14_ $end
$var wire 1 0 _13_ $end
$var wire 1 1 _12_ $end
$var wire 1 2 _11_ $end
$var wire 1 3 _10_ $end
$var wire 1 4 _09_ $end
$var wire 1 5 _08_ $end
$var wire 1 6 _07_ $end
$var wire 1 7 _06_ $end
$var wire 1 8 _05_ $end
$var wire 1 9 _04_ $end
$var wire 1 : _03_ $end
$var wire 1 ; _02_ $end
$var wire 1 < _01_ $end
$var wire 1 = _00_ $end
$scope module _19_ $end
$var wire 1 > A $end
$var wire 1 ? B $end
$var wire 1 4 X $end
$upscope $end
$scope module _20_ $end
$var wire 1 4 A $end
$var wire 1 3 Y $end
$upscope $end
$scope module _21_ $end
$var wire 1 & A $end
$var wire 1 2 Y $end
$upscope $end
$scope module _22_ $end
$var wire 1 3 A2 $end
$var wire 1 @ B1 $end
$var wire 1 4 B2 $end
$var wire 1 2 C1 $end
$var wire 1 6 X $end
$var wire 1 A or0_out $end
$var wire 1 B or1_out $end
$var wire 1 . A1 $end
$upscope $end
$scope module _23_ $end
$var wire 1 3 A2 $end
$var wire 1 C B1 $end
$var wire 1 4 B2 $end
$var wire 1 2 C1 $end
$var wire 1 7 X $end
$var wire 1 D or0_out $end
$var wire 1 E or1_out $end
$var wire 1 , A1 $end
$upscope $end
$scope module _24_ $end
$var wire 1 3 A2 $end
$var wire 1 F B1 $end
$var wire 1 4 B2 $end
$var wire 1 2 C1 $end
$var wire 1 8 X $end
$var wire 1 G or0_out $end
$var wire 1 H or1_out $end
$var wire 1 - A1 $end
$upscope $end
$scope module _25_ $end
$var wire 1 I A $end
$var wire 1 1 X $end
$upscope $end
$scope module _26_ $end
$var wire 1 1 A $end
$var wire 1 = Y $end
$upscope $end
$scope module _27_ $end
$var wire 1 J A $end
$var wire 1 0 X $end
$upscope $end
$scope module _28_ $end
$var wire 1 = A $end
$var wire 1 0 B $end
$var wire 1 / Y $end
$upscope $end
$scope module _29_ $end
$var wire 1 1 A1 $end
$var wire 1 0 A2 $end
$var wire 1 K A3 $end
$var wire 1 L B1 $end
$var wire 1 / B2 $end
$var wire 1 < X $end
$var wire 1 M and0_out $end
$var wire 1 N and1_out $end
$upscope $end
$scope module _30_ $end
$var wire 1 1 A1 $end
$var wire 1 0 A2 $end
$var wire 1 O A3 $end
$var wire 1 % B1 $end
$var wire 1 / B2 $end
$var wire 1 ; X $end
$var wire 1 P and0_out $end
$var wire 1 Q and1_out $end
$upscope $end
$scope module _31_ $end
$var wire 1 1 A1 $end
$var wire 1 0 A2 $end
$var wire 1 R A3 $end
$var wire 1 S B1 $end
$var wire 1 / B2 $end
$var wire 1 : X $end
$var wire 1 T and0_out $end
$var wire 1 U and1_out $end
$upscope $end
$scope module _32_ $end
$var wire 1 1 A1 $end
$var wire 1 0 A2 $end
$var wire 1 V A3 $end
$var wire 1 W B1 $end
$var wire 1 / B2 $end
$var wire 1 9 X $end
$var wire 1 X and0_out $end
$var wire 1 Y and1_out $end
$upscope $end
$scope module _33_ $end
$var wire 1 3 A2 $end
$var wire 1 Z B1 $end
$var wire 1 4 B2 $end
$var wire 1 2 C1 $end
$var wire 1 5 X $end
$var wire 1 [ or0_out $end
$var wire 1 \ or1_out $end
$var wire 1 + A1 $end
$upscope $end
$scope module _34_ $end
$var wire 1 < A0 $end
$var wire 1 # A1 $end
$var wire 1 = S $end
$var wire 1 , X $end
$var wire 1 ] and_out0 $end
$var wire 1 ^ and_out1 $end
$var wire 1 _ not_out $end
$upscope $end
$scope module _35_ $end
$var wire 1 ; A0 $end
$var wire 1 ` A1 $end
$var wire 1 = S $end
$var wire 1 + X $end
$var wire 1 a and_out0 $end
$var wire 1 b and_out1 $end
$var wire 1 c not_out $end
$upscope $end
$scope module _36_ $end
$var wire 1 : A0 $end
$var wire 1 d A1 $end
$var wire 1 = S $end
$var wire 1 . X $end
$var wire 1 e and_out0 $end
$var wire 1 f and_out1 $end
$var wire 1 g not_out $end
$upscope $end
$scope module _37_ $end
$var wire 1 9 A0 $end
$var wire 1 h A1 $end
$var wire 1 = S $end
$var wire 1 - X $end
$var wire 1 i and_out0 $end
$var wire 1 j and_out1 $end
$var wire 1 k not_out $end
$upscope $end
$scope module _38_ $end
$var wire 1 " CLK $end
$var wire 1 8 D $end
$var reg 1 l Q $end
$upscope $end
$scope module _39_ $end
$var wire 1 " CLK $end
$var wire 1 7 D $end
$var reg 1 m Q $end
$upscope $end
$scope module _40_ $end
$var wire 1 " CLK $end
$var wire 1 6 D $end
$var reg 1 n Q $end
$upscope $end
$scope module _41_ $end
$var wire 1 " CLK $end
$var wire 1 5 D $end
$var reg 1 o Q $end
$upscope $end
$upscope $end
$upscope $end
$enddefinitions $end
#0
$dumpvars
xo
xn
xm
xl
xk
xj
xi
xh
xg
xf
xe
xd
xc
xb
xa
x`
x_
x^
x]
x\
x[
xZ
xY
xX
xW
xV
xU
xT
xS
xR
xQ
xP
xO
xN
xM
xL
xK
xJ
xI
xH
xG
xF
xE
xD
xC
xB
xA
x@
x?
x>
x=
x<
x;
x:
x9
x8
x7
x6
x5
x4
x3
x2
x1
x0
x/
x.
x-
x,
x+
bx *
bx )
bx (
bx '
x&
x%
bx $
x#
0"
bx !
$end
#1000
0<
0;
0:
09
0N
0Q
0U
0Y
0]
1,
0a
0e
0i
1B
1E
1H
1\
0/
0_
1^
0c
0g
0k
13
1=
0M
0P
0T
0X
04
01
00
06
07
08
05
0K
0O
0R
0V
0>
0?
0I
0J
02
b0 $
b0 (
1%
1#
b0 '
b0 )
1&
#2000
0+
0.
0-
0b
0G
0f
0D
0j
0A
0[
0`
0S
0F
0d
0C
0h
0L
0@
0Z
0W
0l
0m
0n
b0 !
b0 *
0o
1"
#4000
0"
#5000
12
0&
#6000
1"
#8000
0"
#9000
0E
1.
1-
0,
1e
1i
1B
1H
0\
16
07
18
05
1_
0^
1c
1g
1k
1:
19
03
1A
1D
1G
1[
0=
1T
1X
14
11
10
1R
1V
1>
1?
1I
1J
b110 $
b110 (
b11 '
b11 )
#10000
1`
1S
1F
1h
1L
1@
1l
b110 !
b110 *
1n
1"
#12000
0"
#13000
0.
1,
1+
0<
0;
0e
0i
1E
1\
0_
1^
0c
1b
0g
0k
1j
0N
0Q
0U
0:
09
13
0D
0[
1=
0/
0T
0X
04
01
00
1O
0V
0>
0?
0I
0J
b1010 $
b1010 (
b0 '
b0 )
#14000
1"
#16000
0"
#17000
1.
1]
1a
1e
08
1<
1;
1:
1E
1\
0H
16
1N
1Q
1U
1,
1+
0-
1B
17
15
1/
1_
0^
1c
0b
1g
1k
0j
03
1D
1[
0=
14
11
1>
1I
b1 '
b1 )
#18000
06
18
0B
1H
0.
1-
0e
1i
0:
19
0U
1Y
0`
0S
0F
1d
1C
1Z
1W
0l
1m
b1011 !
b1011 *
1o
1"
#20000
0"
#21000
05
0\
16
0+
1B
0]
0a
1.
0i
0<
0;
09
0_
1^
0c
0g
1f
0k
1j
0N
0Q
0Y
1=
0/
01
10
0>
1?
0I
1J
b10 '
b10 )
#22000
15
1\
1+
1b
0Z
0W
1`
1S
1F
0o
b111 !
b111 *
1l
1"
#24000
0"
#25000
05
13
0[
04
00
1K
0O
0R
0?
0J
b1 $
b1 (
b0 '
b0 )
#26000
1"
#28000
0"
#29000
1]
1a
1e
17
16
08
1<
1;
1:
1E
1\
1B
0H
1N
1Q
1U
1,
1+
1.
0-
15
1/
1_
0^
1c
0b
1g
0f
1k
0j
03
1[
0=
14
11
0K
1O
1R
1>
1I
b1010 $
b1010 (
b1 '
b1 )
#30000
18
06
1H
0B
1-
0.
1i
0e
19
0:
1Y
0U
1Z
1W
0`
0S
0F
1o
b1011 !
b1011 *
0l
1"
#32000
0"
#33000
05
0\
16
0+
1B
0]
0a
1.
0i
0<
0;
09
0_
1^
0c
0g
1f
0k
1j
0N
0Q
0Y
1=
0/
01
10
0>
1?
0I
1J
b10 '
b10 )
#34000
15
1\
1+
1b
1`
1S
1F
0Z
0W
1l
b111 !
b111 *
0o
1"
